azure/ai/metricsadvisor/__init__.py
azure/ai/metricsadvisor/_client.py
azure/ai/metricsadvisor/_configuration.py
azure/ai/metricsadvisor/_patch.py
azure/ai/metricsadvisor/_vendor.py
azure/ai/metricsadvisor/_version.py
azure/ai/metricsadvisor/py.typed
azure/ai/metricsadvisor/_operations/__init__.py
azure/ai/metricsadvisor/_operations/_operations.py
azure/ai/metricsadvisor/_operations/_patch.py
azure/ai/metricsadvisor/aio/__init__.py
azure/ai/metricsadvisor/aio/_client.py
azure/ai/metricsadvisor/aio/_configuration.py
azure/ai/metricsadvisor/aio/_patch.py
azure/ai/metricsadvisor/aio/_vendor.py
azure/ai/metricsadvisor/aio/_operations/__init__.py
azure/ai/metricsadvisor/aio/_operations/_operations.py
azure/ai/metricsadvisor/aio/_operations/_patch.py
azure/ai/metricsadvisor/models/__init__.py
azure/ai/metricsadvisor/models/_enums.py
azure/ai/metricsadvisor/models/_models.py
azure/ai/metricsadvisor/models/_patch.py
azure_ai_metricsadvisor-1.0.1.dist-info/LICENSE
azure_ai_metricsadvisor-1.0.1.dist-info/METADATA
azure_ai_metricsadvisor-1.0.1.dist-info/WHEEL
azure_ai_metricsadvisor-1.0.1.dist-info/top_level.txt
azure_ai_metricsadvisor-1.0.1.dist-info/RECORD
